feistelcipher/CryptFunctions.py
feistelcipher/FeistelCipher.py
feistelcipher/StandardCryptFunctions.py
feistelcipher/__init__.py
feistelcipher-0.2.0.dist-info/METADATA
feistelcipher-0.2.0.dist-info/WHEEL
feistelcipher-0.2.0.dist-info/top_level.txt
feistelcipher-0.2.0.dist-info/RECORD
