Metadata-Version: 2.1
Name: feistelcipher
Version: 0.2.0
Summary: Naive implementation of Feistel Cipher for encrypting/decrypting integers using custom function blocks.
Home-page: https://github.com/mayur7garg/FeistelCipher
Author: Mayur Kr. Garg
Author-email: mayur7garg@gmail.com
License: MIT
Platform: UNKNOWN
Classifier: License :: OSI Approved :: MIT License
Classifier: Programming Language :: Python :: 3
Classifier: Programming Language :: Python :: 3.7
